odoo9_addon_stock_reserve_sale-9.0.1.0.0.99.dev5-nspkg.pth
odoo_addons/stock_reserve_sale/README.rst
odoo_addons/stock_reserve_sale/__init__.py
odoo_addons/stock_reserve_sale/__openerp__.py
odoo_addons/stock_reserve_sale/i18n/es.po
odoo_addons/stock_reserve_sale/i18n/fi.po
odoo_addons/stock_reserve_sale/i18n/fr.po
odoo_addons/stock_reserve_sale/i18n/stock_reserve_sale.pot
odoo_addons/stock_reserve_sale/model/__init__.py
odoo_addons/stock_reserve_sale/model/sale.py
odoo_addons/stock_reserve_sale/model/stock_reserve.py
odoo_addons/stock_reserve_sale/security/ir.model.access.csv
odoo_addons/stock_reserve_sale/static/description/icon.png
odoo_addons/stock_reserve_sale/test/sale_line_reserve.yml
odoo_addons/stock_reserve_sale/test/sale_reserve.yml
odoo_addons/stock_reserve_sale/view/sale.xml
odoo_addons/stock_reserve_sale/view/stock_reserve.xml
odoo_addons/stock_reserve_sale/wizard/__init__.py
odoo_addons/stock_reserve_sale/wizard/sale_stock_reserve.py
odoo_addons/stock_reserve_sale/wizard/sale_stock_reserve_view.xml
odoo9_addon_stock_reserve_sale-9.0.1.0.0.99.dev5.dist-info/METADATA
odoo9_addon_stock_reserve_sale-9.0.1.0.0.99.dev5.dist-info/WHEEL
odoo9_addon_stock_reserve_sale-9.0.1.0.0.99.dev5.dist-info/namespace_packages.txt
odoo9_addon_stock_reserve_sale-9.0.1.0.0.99.dev5.dist-info/top_level.txt
odoo9_addon_stock_reserve_sale-9.0.1.0.0.99.dev5.dist-info/RECORD
